SiNN/SiCNN.py
SiNN/__init__.py
SiNN-0.0.3.dist-info/METADATA
SiNN-0.0.3.dist-info/RECORD
SiNN-0.0.3.dist-info/WHEEL
SiNN-0.0.3.dist-info/top_level.txt
