Metadata-Version: 2.1
Name: SiNN
Version: 0.0.3
Summary: A simple way to make neural nets: Machine learning without linear algebra
Home-page: https://github.com/pithonmath/neuralnet
Author: SiCNN Author
Author-email: lincolnauster@gmail.com
License: UNKNOWN
Platform: UNKNOWN
Classifier: Programming Language :: Python :: 3
Classifier: License :: OSI Approved :: MIT License
Classifier: Operating System :: OS Independent
